ntnu/kt/__init__.py
ntnu/kt/course/__init__.py
ntnu/kt/course/tkt4116.py
ntnu.kt-0.0.8.dist-info/METADATA
ntnu.kt-0.0.8.dist-info/WHEEL
ntnu.kt-0.0.8.dist-info/top_level.txt
ntnu.kt-0.0.8.dist-info/RECORD
