Metadata-Version: 2.1
Name: ntnu.kt
Version: 0.0.8
Summary: Standard library for NTNU Konstruksjonsteknikk
Home-page: https://github.com/ntnu-kt/ntnu.kt
Author: Teodor Heggelund
Author-email: teodor.heggelund@gmail.com
License: MIT
Platform: UNKNOWN
